airsimneurips/__init__.py
airsimneurips/baseline.py
airsimneurips/client.py
airsimneurips/pfm.py
airsimneurips/types.py
airsimneurips/utils.py
airsimneurips-1.2.0.dist-info/DESCRIPTION.rst
airsimneurips-1.2.0.dist-info/METADATA
airsimneurips-1.2.0.dist-info/RECORD
airsimneurips-1.2.0.dist-info/WHEEL
airsimneurips-1.2.0.dist-info/metadata.json
airsimneurips-1.2.0.dist-info/top_level.txt
