Metadata-Version: 2.0
Name: airsimneurips
Version: 1.2.0
Summary: Python package for Game of Drones - A NeurIPS 2019 Competition, built on Microsoft AirSim - an open source simulator based on Unreal Engine for autonomous vehicles from Microsoft AI & Research
Home-page: https://github.com/microsoft/AirSim-NeurIPS2019-Drone-Racing
Author: Ratnesh Madaan, Matthew Brown, Nicholas Gyde, Sai Vemprala, Shital Shah
Author-email: ratnesh.madaan@microsoft.com, v-mattbr@microsoft.com, v-nigyde@microsoft.com, sai.vemprala@microsoft.com, shitals@microsoft.com
License: MIT
Platform: UNKNOWN
Classifier: Programming Language :: Python :: 3
Classifier: License :: OSI Approved :: MIT License
Classifier: Operating System :: OS Independent
Requires-Dist: msgpack-rpc-python
Requires-Dist: numpy (<=1.16)
